crossdb_query.py
crossdb_query-0.0.2.dist-info/LICENSE
crossdb_query-0.0.2.dist-info/METADATA
crossdb_query-0.0.2.dist-info/WHEEL
crossdb_query-0.0.2.dist-info/entry_points.txt
crossdb_query-0.0.2.dist-info/top_level.txt
crossdb_query-0.0.2.dist-info/RECORD
