Metadata-Version: 2.1
Name: crossdb_query
Version: 0.0.2
Summary: Execute a SQL file on all PostgreSQL databases on a host.
Author-email: Caleb Grant <grantcaleb22@gmail.com>
License: GNU GENERAL PUBLIC LICENSE
Project-URL: Repository, https://github.com/geocoug/crossdb-query
Project-URL: Issues, https://github.com/geocoug/crossdb-query/issues
Keywords: postgres,postgresql,sql,database,query,crossdb
Classifier: Programming Language :: Python :: 3
Classifier: Programming Language :: Python :: 3.10
Classifier: Programming Language :: Python :: 3.11
Classifier: Programming Language :: Python :: 3.12
Classifier: Operating System :: OS Independent
Classifier: Intended Audience :: Developers
Classifier: Topic :: Software Development :: Libraries :: Python Modules
Classifier: License :: OSI Approved :: GNU Lesser General Public License v3 (LGPLv3)
Requires-Python: >=3.10
License-File: LICENSE
Requires-Dist: psycopg2-binary >=2.9.9
